drf_email_auth/__init__.py
drf_email_auth/admin.py
drf_email_auth/apps.py
drf_email_auth/manager.py
drf_email_auth/models.py
drf_email_auth/serializers.py
drf_email_auth/urls.py
drf_email_auth/views.py
tests/__init__.py
tests/test_models.py
tests/test_serializers.py
tests/test_views.py
drf_email_auth-0.1.dist-info/LICENSE
drf_email_auth-0.1.dist-info/METADATA
drf_email_auth-0.1.dist-info/WHEEL
drf_email_auth-0.1.dist-info/top_level.txt
drf_email_auth-0.1.dist-info/RECORD
