Metadata-Version: 2.1
Name: drf-email-auth
Version: 0.1
Summary: A DRF package for email-based authentication
Home-page: https://github.com/aakash-shakya/django-email-auth
Author: Aakash Shakya
Author-email: official.aakas@gmail.com
License: MIT License
Platform: UNKNOWN
Classifier: Environment :: Web Environment
Classifier: Framework :: Django
Classifier: Framework :: Django :: 3.2
Classifier: Framework :: Django :: 4.0
Classifier: Programming Language :: Python :: 3
Classifier: Programming Language :: Python :: 3.7
Classifier: Programming Language :: Python :: 3.8
Classifier: Programming Language :: Python :: 3.9
Classifier: Programming Language :: Python :: 3.10
Classifier: License :: OSI Approved :: MIT License
Classifier: Operating System :: OS Independent
License-File: LICENSE
Requires-Dist: Django (>=3.2)
Requires-Dist: djangorestframework
Requires-Dist: djangorestframework-simplejwt
